memes/__init__.py
memes/memes.py
python_memes-0.1.1.dist-info/licenses/LICENSE
python_memes-0.1.1.dist-info/METADATA
python_memes-0.1.1.dist-info/WHEEL
python_memes-0.1.1.dist-info/top_level.txt
python_memes-0.1.1.dist-info/RECORD
