Metadata-Version: 2.4
Name: python-memes
Version: 0.1.1
Summary: A simple Python package to fetch random memes from Reddit.
Author-email: Madhav <kathuriamadhav0703@gmail.com>
License: MIT License
Keywords: memes,reddit,fun,api
Classifier: Development Status :: 3 - Alpha
Classifier: Intended Audience :: Developers
Classifier: Topic :: Software Development :: Libraries
Classifier: Programming Language :: Python :: 3
Classifier: Programming Language :: Python :: 3.8
Classifier: Programming Language :: Python :: 3.9
Classifier: Programming Language :: Python :: 3.10
Classifier: License :: OSI Approved :: MIT License
Classifier: Operating System :: OS Independent
Requires-Python: >=3.8
License-File: LICENSE
Requires-Dist: requests>=2.28.0
Dynamic: license-file
